upsetplotly/__init__.py
upsetplotly/plotting.py
upsetplotly/set_functions.py
UpSetPlotly-0.1.7.dist-info/METADATA
UpSetPlotly-0.1.7.dist-info/WHEEL
UpSetPlotly-0.1.7.dist-info/top_level.txt
UpSetPlotly-0.1.7.dist-info/RECORD
